LICENSE
MANIFEST.in
README.md
setup.cfg
setup.py
docassemble/__init__.py
docassemble.VRF.egg-info/PKG-INFO
docassemble.VRF.egg-info/SOURCES.txt
docassemble.VRF.egg-info/dependency_links.txt
docassemble.VRF.egg-info/namespace_packages.txt
docassemble.VRF.egg-info/not-zip-safe
docassemble.VRF.egg-info/top_level.txt
docassemble/VRF/__init__.py
docassemble/VRF/data/questions/VRF.yml
docassemble/VRF/data/sources/README.md
docassemble/VRF/data/static/README.md
docassemble/VRF/data/templates/README.md
docassemble/VRF/data/templates/Video_Release_Form.docx