Metadata-Version: 2.1
Name: docassemble.VRF
Version: 0.0.1
Summary: A docassemble extension.
Home-page: https://docassemble.org
Author: System Administrator
Author-email: admin@admin.com
License: The MIT License (MIT)
Platform: UNKNOWN
